pywtdlib/__init__.py
pywtdlib/client.py
pywtdlib/enum.py
pywtdlib/tdjson.py
pywtdlib/lib/Linux/aarch64/libtdjson.so
pywtdlib/lib/Linux/aarch64/libtdjson.so.1.8.9
pywtdlib/lib/Linux/armv7l/libtdjson.so
pywtdlib/lib/Linux/armv7l/libtdjson.so.1.7.9
pywtdlib/lib/Linux/x86_64/libtdjson.so
pywtdlib/lib/Linux/x86_64/libtdjson.so.1.8.9
pywtdlib/lib/Windows/AMD64/libcrypto-1_1-x64.dll
pywtdlib/lib/Windows/AMD64/libssl-1_1-x64.dll
pywtdlib/lib/Windows/AMD64/libtdjson.dll
pywtdlib/lib/Windows/AMD64/zlib1.dll
pywtdlib-0.2.0.dist-info/LICENSE
pywtdlib-0.2.0.dist-info/METADATA
pywtdlib-0.2.0.dist-info/WHEEL
pywtdlib-0.2.0.dist-info/top_level.txt
pywtdlib-0.2.0.dist-info/RECORD
