Metadata-Version: 2.1
Name: pywtdlib
Version: 0.2.0
Summary: A simple Python TDLib wrapper
Home-page: https://github.com/alvhix/pywtdlib
Author: alvhix
Author-email: alvhix@gmail.com
Project-URL: Bug Tracker, https://github.com/alvhix/pywtdlib/issues
Classifier: Programming Language :: Python :: 3
Classifier: License :: OSI Approved :: MIT License
Classifier: Operating System :: OS Independent
Requires-Python: >=3.6
License-File: LICENSE
